{"assets":{"0FF513F94AB6306A7714EED4EBCB0628":{"type":"texture","index":0,"url":{"native":"assets\/615F0023-B514-4DAE-BDE3-F49C523A0934.pdf"},"width":1920,"height":1080},"2BC14E77C7A223F620296987FCBE511E":{"type":"texture","index":1,"url":{"native":"assets\/615F0023-B514-4DAE-BDE3-F49C523A0934.pdf"},"width":1920,"height":1080}},"events":[{"effects":[{"beginTime":0,"baseLayer":{"animations":[],"initialState":{"affineTransform":[1,0,0,1,0,0],"masksToBounds":false,"rotation":0,"scale":1,"position":{"pointX":960,"pointY":540},"width":1920,"sublayerTransform":[1,0,0,0,0,1,0,0,0,0,1,0,0,0,0,1],"contentsRect":{"y":0,"x":0,"width":1,"height":1},"opacity":1,"edgeAntialiasingMask":251658240,"height":1080,"hidden":false,"anchorPoint":{"pointX":0.5,"pointY":0.5}},"objectID":"0","layers":[{"animations":[],"initialState":{"affineTransform":[1,0,0,1,0,0],"masksToBounds":false,"rotation":0,"scale":1,"position":{"pointX":960,"pointY":540},"width":1920,"sublayerTransform":[1,0,0,0,0,1,0,0,0,0,1,-0.00035007912466775983,0,0,0,1],"contentsRect":{"y":0,"x":0,"width":1,"height":1},"opacity":1,"edgeAntialiasingMask":251658240,"height":1080,"hidden":false,"anchorPoint":{"pointX":0.5,"pointY":0.5}},"layers":[{"animations":[],"layers":[],"texturedRectangle":{"isBackgroundTexture":false,"singleTextureOpacity":1,"textureType":0,"textBaseline":0,"textXHeight":0,"isVerticalText":false},"initialState":{"affineTransform":[1,0,0,1,0,0],"masksToBounds":false,"rotation":0,"scale":1,"position":{"pointX":960,"pointY":540},"width":1920,"sublayerTransform":[1,0,0,0,0,1,0,0,0,0,1,0,0,0,0,1],"contentsRect":{"y":0,"x":0,"width":1,"height":1},"opacity":1,"edgeAntialiasingMask":0,"height":1080,"hidden":false,"anchorPoint":{"pointX":0.5,"pointY":0.5}},"texture":"2BC14E77C7A223F620296987FCBE511E"},{"animations":[{"additive":false,"timeOffset":0,"beginTime":0,"from":{"scalar":false},"repeatCount":0,"fillMode":"both","duration":0.001,"autoreverses":false,"property":"hidden","to":{"scalar":true},"removedOnCompletion":false}],"layers":[],"texturedRectangle":{"isBackgroundTexture":false,"singleTextureOpacity":1,"textureType":0,"textBaseline":0,"textXHeight":0,"isVerticalText":false},"initialState":{"affineTransform":[1,0,0,1,0,0],"masksToBounds":false,"rotation":0,"scale":1,"position":{"pointX":960,"pointY":540},"width":1920,"sublayerTransform":[1,0,0,0,0,1,0,0,0,0,1,0,0,0,0,1],"contentsRect":{"y":0,"x":0,"width":1,"height":1},"opacity":1,"edgeAntialiasingMask":0,"height":1080,"hidden":false,"anchorPoint":{"pointX":0.5,"pointY":0.5}},"texture":"0FF513F94AB6306A7714EED4EBCB0628"}]}]},"effects":[],"duration":0.001,"type":"transition","attributes":{"direction":0},"name":"none","objectID":"0"}],"automaticPlay":false,"hyperlinks":[{"url":"https:\/\/letsencrypt.org\/","targetRectangle":{"y":90.199999550852581,"x":1488.6172163867343,"width":418.20000000000005,"height":52.599999189376817}}],"accessibility":[{"text":"L’appareil du client vient pré-installé avec un “magasin de confiance” (trust store) contenant:","targetRectangle":{"y":338.52792358398438,"x":134.27999975204466,"width":1637.4624000000006,"height":51.607999205589294}},{"text":"Nom de l’autorité de confiance","targetRectangle":{"y":390.52792358398438,"x":170.27999975204466,"width":548.32960000000014,"height":97.668000102043152}},{"text":"Clé publique de l’autorité de confiance","targetRectangle":{"y":488.58792448043823,"x":170.27999975204466,"width":686.74480000000005,"height":97.668000102043152}},{"text":"Le serveur possède un certificat préalablement signé par l’autorité de confiance contenant:","targetRectangle":{"y":586.64792537689209,"x":134.27999975204466,"width":1625.7808,"height":97.668000102043152}},{"text":"Nom du serveur","targetRectangle":{"y":684.70792627334595,"x":170.27999975204466,"width":284.16080000000005,"height":97.668000102043152}},{"text":"Nom de l’autorité de confiance","targetRectangle":{"y":782.7679271697998,"x":170.27999975204466,"width":548.32960000000014,"height":97.668000102043152}},{"text":"Clé publique du serveur","targetRectangle":{"y":880.82792806625366,"x":170.27999975204466,"width":422.57600000000002,"height":97.668000102043152}},{"text":"Certification signée par une autorité de confiance","targetRectangle":{"y":186.59999990463257,"x":98.599999904632568,"width":1246.2999999999995,"height":71.449998885393143}},{"text":"Établissement de clé","targetRectangle":{"y":54,"x":99,"width":884.54500040344908,"height":124.04999807476997}},{"text":"Shoutout to: https:\/\/letsencrypt.org\/","targetRectangle":{"y":90.199999550852581,"x":1254.5772163867343,"width":652.24000000000001,"height":52.599999189376817}}],"baseLayer":{"animations":[],"initialState":{"affineTransform":[1,0,0,1,0,0],"masksToBounds":false,"rotation":0,"scale":1,"position":{"pointX":960,"pointY":540},"width":1920,"sublayerTransform":[1,0,0,0,0,1,0,0,0,0,1,0,0,0,0,1],"contentsRect":{"y":0,"x":0,"width":1,"height":1},"opacity":1,"edgeAntialiasingMask":251658240,"height":1080,"hidden":false,"anchorPoint":{"pointX":0.5,"pointY":0.5}},"objectID":"0","layers":[{"animations":[],"initialState":{"affineTransform":[1,0,0,1,0,0],"masksToBounds":false,"rotation":0,"scale":1,"position":{"pointX":960,"pointY":540},"width":1920,"sublayerTransform":[1,0,0,0,0,1,0,0,0,0,1,-0.00035007912466775983,0,0,0,1],"contentsRect":{"y":0,"x":0,"width":1,"height":1},"opacity":1,"edgeAntialiasingMask":251658240,"height":1080,"hidden":false,"anchorPoint":{"pointX":0.5,"pointY":0.5}},"layers":[{"animations":[],"layers":[],"texturedRectangle":{"isBackgroundTexture":false,"singleTextureOpacity":1,"textureType":0,"textBaseline":0,"textXHeight":0,"isVerticalText":false},"initialState":{"affineTransform":[1,0,0,1,0,0],"masksToBounds":false,"rotation":0,"scale":1,"position":{"pointX":960,"pointY":540},"width":1920,"sublayerTransform":[1,0,0,0,0,1,0,0,0,0,1,0,0,0,0,1],"contentsRect":{"y":0,"x":0,"width":1,"height":1},"opacity":1,"edgeAntialiasingMask":0,"height":1080,"hidden":false,"anchorPoint":{"pointX":0.5,"pointY":0.5}},"texture":"0FF513F94AB6306A7714EED4EBCB0628"}]}]}}]}